[
    {
        "ID Tarefa": "32",
        "Título Tarefa": "Ola",
        "Subtarefa": "1",
        "Título Subtarefa": "Texto_Ola",
        "Tipo Subtarefa": "Texto",
        "Descrição": "oi",
        "Data Cadastro": "2025-06-07",
        "Data Entrega": "2025-06-18"
    },
    {
        "ID Tarefa": "32",
        "Título Tarefa": "Ola",
        "Subtarefa": "2",
        "Título Subtarefa": "Layout_Ola",
        "Tipo Subtarefa": "Layout",
        "Descrição": "oi",
        "Data Cadastro": "2025-06-07",
        "Data Entrega": "2025-06-19"
    },
    {
        "ID Tarefa": "32",
        "Título Tarefa": "Ola",
        "Subtarefa": "3",
        "Título Subtarefa": "HTML_Ola",
        "Tipo Subtarefa": "HTML",
        "Descrição": "oi",
        "Data Cadastro": "2025-06-07",
        "Data Entrega": "2025-06-20"
    },
    {
        "ID Tarefa": "33",
        "Título Tarefa": "Ola 2",
        "Subtarefa": "1",
        "Título Subtarefa": "Texto_Ola 2",
        "Tipo Subtarefa": "Texto",
        "Descrição": "oi",
        "Data Cadastro": "2025-06-07",
        "Data Entrega": "2025-06-18"
    },
    {
        "ID Tarefa": "33",
        "Título Tarefa": "Ola 2",
        "Subtarefa": "2",
        "Título Subtarefa": "Layout_Ola 2",
        "Tipo Subtarefa": "Layout",
        "Descrição": "oi",
        "Data Cadastro": "2025-06-07",
        "Data Entrega": "2025-06-19"
    },
    {
        "ID Tarefa": "33",
        "Título Tarefa": "Ola 2",
        "Subtarefa": "3",
        "Título Subtarefa": "HTML_Ola 2",
        "Tipo Subtarefa": "HTML",
        "Descrição": "oi",
        "Data Cadastro": "2025-06-07",
        "Data Entrega": "2025-06-20"
    },
    {
        "ID Tarefa": "34",
        "Título Tarefa": "teste",
        "Subtarefa": "1",
        "Título Subtarefa": "Texto_teste",
        "Tipo Subtarefa": "Texto",
        "Descrição": "oi",
        "Data Cadastro": "2025-06-07",
        "Data Entrega": "2025-06-18"
    },
    {
        "ID Tarefa": "34",
        "Título Tarefa": "teste",
        "Subtarefa": "2",
        "Título Subtarefa": "Layout_teste",
        "Tipo Subtarefa": "Layout",
        "Descrição": "oi",
        "Data Cadastro": "2025-06-07",
        "Data Entrega": "2025-06-19"
    },
    {
        "ID Tarefa": "34",
        "Título Tarefa": "teste",
        "Subtarefa": "3",
        "Título Subtarefa": "HTML_teste",
        "Tipo Subtarefa": "HTML",
        "Descrição": "oi",
        "Data Cadastro": "2025-06-07",
        "Data Entrega": "2025-06-20"
    },
    {
        "ID Tarefa": "31",
        "Título Tarefa": "sssssssss",
        "Subtarefa": "1",
        "Título Subtarefa": "Texto_sssssssss",
        "Tipo Subtarefa": "Texto",
        "Descrição": "aaaaaaaaaaaaaa",
        "Data Cadastro": "2025-06-09",
        "Data Entrega": "2025-07-15"
    },
    {
        "ID Tarefa": "31",
        "Título Tarefa": "sssssssss",
        "Subtarefa": "2",
        "Título Subtarefa": "Layout_sssssssss",
        "Tipo Subtarefa": "Layout",
        "Descrição": "aaaaaaaaaaaaaa",
        "Data Cadastro": "2025-06-09",
        "Data Entrega": "2025-07-16"
    },
    {
        "ID Tarefa": "35",
        "Título Tarefa": "Jornada Bolo COOP",
        "Subtarefa": "1",
        "Título Subtarefa": "Texto_Jornada Bolo COOP",
        "Tipo Subtarefa": "Texto",
        "Descrição": "oii",
        "Data Cadastro": "2025-06-09",
        "Data Entrega": "2025-06-09"
    },
    {
        "ID Tarefa": "37",
        "Título Tarefa": "ola",
        "Subtarefa": "1",
        "Título Subtarefa": "Texto_ola",
        "Tipo Subtarefa": "Texto",
        "Descrição": "",
        "Data Cadastro": "2025-06-09",
        "Data Entrega": "2025-06-24"
    },
    {
        "ID Tarefa": "37",
        "Título Tarefa": "ola",
        "Subtarefa": "2",
        "Título Subtarefa": "Layout_ola",
        "Tipo Subtarefa": "Layout",
        "Descrição": "",
        "Data Cadastro": "2025-06-09",
        "Data Entrega": "2025-06-25"
    },
    {
        "ID Tarefa": "37",
        "Título Tarefa": "ola",
        "Subtarefa": "3",
        "Título Subtarefa": "HTML_ola",
        "Tipo Subtarefa": "HTML",
        "Descrição": "",
        "Data Cadastro": "2025-06-09",
        "Data Entrega": "2025-06-26"
    },
    {
        "ID Tarefa": "40",
        "Título Tarefa": "Natal",
        "Subtarefa": "1",
        "Título Subtarefa": "Texto_Natal",
        "Tipo Subtarefa": "Texto",
        "Descrição": "Festa",
        "Data Cadastro": "2025-06-10",
        "Data Entrega": "2025-12-24"
    },
    {
        "ID Tarefa": "40",
        "Título Tarefa": "Natal",
        "Subtarefa": "2",
        "Título Subtarefa": "Layout_Natal",
        "Tipo Subtarefa": "Layout",
        "Descrição": "Festa",
        "Data Cadastro": "2025-06-10",
        "Data Entrega": "2025-12-24"
    },
    {
        "ID Tarefa": "41",
        "Título Tarefa": "gui",
        "Subtarefa": "1",
        "Título Subtarefa": "Texto_gui",
        "Tipo Subtarefa": "Texto",
        "Descrição": "",
        "Data Cadastro": "2025-06-10",
        "Data Entrega": "2025-06-10"
    },
    {
        "ID Tarefa": "41",
        "Título Tarefa": "gui",
        "Subtarefa": "2",
        "Título Subtarefa": "Layout_gui",
        "Tipo Subtarefa": "Layout",
        "Descrição": "",
        "Data Cadastro": "2025-06-10",
        "Data Entrega": "2025-06-10"
    },
    {
        "ID Tarefa": "41",
        "Título Tarefa": "gui",
        "Subtarefa": "3",
        "Título Subtarefa": "HTML_gui",
        "Tipo Subtarefa": "HTML",
        "Descrição": "",
        "Data Cadastro": "2025-06-10",
        "Data Entrega": "2025-06-11"
    }
]